src/__init__.py
src/rubyx.py
src/rubyx_api.py
src/test/__init__.py
src/test/rubyx_test.py
rubyx-1.0.0.dist-info/METADATA
rubyx-1.0.0.dist-info/WHEEL
rubyx-1.0.0.dist-info/entry_points.txt
rubyx-1.0.0.dist-info/top_level.txt
rubyx-1.0.0.dist-info/RECORD
