Metadata-Version: 2.1
Name: rubyx
Version: 1.0.0
Summary: Rubyx
Home-page: https://github.com/aituglo/rubyx
Author: @aituglo
Author-email: contact@aituglo.com
Classifier: Programming Language :: Python :: 3
Classifier: License :: OSI Approved :: MIT License
Classifier: Operating System :: OS Independent
Requires-Python: >=3.5
Requires-Dist: docopt
Requires-Dist: requests
